LICENSE
README.md
lbn.py
requirements.txt
setup.py
lbn.egg-info/PKG-INFO
lbn.egg-info/SOURCES.txt
lbn.egg-info/dependency_links.txt
lbn.egg-info/not-zip-safe
lbn.egg-info/requires.txt
lbn.egg-info/top_level.txt