Metadata-Version: 2.1
Name: lbn
Version: 1.2.1
Summary: TensorFlow implementation of the Lorentz Boost Network (LBN). https://arxiv.org/abs/1812.09722.
Home-page: https://github.com/riga/LBN
Author: Marcel Rieger
Author-email: marcel.rieger@cern.ch
License: BSD
Keywords: neural network,lorentz,lorentz transformation,lorentz boost,autonomous,feature,feature engineering,autonomous engineering,hep,four momenta,four vectors
Platform: UNKNOWN
Classifier: Programming Language :: Python
Classifier: Programming Language :: Python :: 2
Classifier: Programming Language :: Python :: 3
Classifier: Development Status :: 4 - Beta
Classifier: Operating System :: OS Independent
Classifier: License :: OSI Approved :: BSD License
Classifier: Intended Audience :: Developers
Classifier: Intended Audience :: Science/Research
Classifier: Intended Audience :: Information Technology
Requires-Python: >=2.7
